Traceline/AsyncLogger.py
Traceline/Config.py
Traceline/Log.py
Traceline/Logger.py
Traceline/Types.py
Traceline/__init__.py
Traceline/py.typed
traceline-0.1.2.dist-info/licenses/LICENSE
traceline-0.1.2.dist-info/METADATA
traceline-0.1.2.dist-info/WHEEL
traceline-0.1.2.dist-info/top_level.txt
traceline-0.1.2.dist-info/RECORD
