Metadata-Version: 2.4
Name: Traceline
Version: 0.1.2
Summary: A high-performance, type-safe asynchronous logging library for Python with ANSI color support, automatic log rotation, and Rust-inspired Result-based error handling.
Author-email: Michael Tang <michaeltang@bionautica.org>
License-Expression: Apache-2.0
Project-URL: Homepage, https://projects.bionautica.org/hyra-zero/traceline
Project-URL: Repository, https://projects.bionautica.org/hyra-zero/traceline.git
Project-URL: Issues, https://projects.bionautica.org/hyra-zero/traceline/-/issues
Project-URL: Changelog, https://projects.bionautica.org/hyra-zero/traceline/-/blob/main/CHANGELOG
Project-URL: Documentation, https://projects.bionautica.org/hyra-zero/traceline/-/blob/main/README.md
Keywords: logging,async,ansi,color,rotation,performance,type-safe,result-pattern,thread-safe
Classifier: Development Status :: 4 - Beta
Classifier: Intended Audience :: Developers
Classifier: Operating System :: OS Independent
Classifier: Programming Language :: Python :: 3
Classifier: Programming Language :: Python :: 3.11
Classifier: Programming Language :: Python :: 3.12
Classifier: Programming Language :: Python :: 3.13
Classifier: Topic :: Software Development :: Libraries :: Python Modules
Classifier: Topic :: System :: Logging
Classifier: Topic :: Software Development :: Quality Assurance
Classifier: Typing :: Typed
Requires-Python: >=3.11
License-File: LICENSE
Requires-Dist: colorama>=0.4.6
Requires-Dist: python-dotenv>=1.1.0
Requires-Dist: returns>=0.25.0
Requires-Dist: typing_extensions>=4.14.0
Provides-Extra: dev
Requires-Dist: pytest>=7.0.0; extra == "dev"
Requires-Dist: pytest-cov>=4.0.0; extra == "dev"
Requires-Dist: pytest-asyncio>=0.21.0; extra == "dev"
Requires-Dist: mypy>=1.0.0; extra == "dev"
Requires-Dist: black>=23.0.0; extra == "dev"
Requires-Dist: isort>=5.12.0; extra == "dev"
Requires-Dist: flake8>=6.0.0; extra == "dev"
Provides-Extra: benchmark
Requires-Dist: pytest-benchmark>=4.0.0; extra == "benchmark"
Dynamic: license-file
